LICENSE
MANIFEST.in
README.md
setup.cfg
setup.py
tap_asana/__init__.py
tap_asana/asana.py
tap_asana/context.py
tap_asana.egg-info/PKG-INFO
tap_asana.egg-info/SOURCES.txt
tap_asana.egg-info/dependency_links.txt
tap_asana.egg-info/entry_points.txt
tap_asana.egg-info/requires.txt
tap_asana.egg-info/top_level.txt
tap_asana/schemas/portfolios.json
tap_asana/schemas/projects.json
tap_asana/schemas/sections.json
tap_asana/schemas/stories.json
tap_asana/schemas/subtasks.json
tap_asana/schemas/tags.json
tap_asana/schemas/tasks.json
tap_asana/schemas/teams.json
tap_asana/schemas/users.json
tap_asana/schemas/workspaces.json
tap_asana/streams/__init__.py
tap_asana/streams/base.py
tap_asana/streams/portfolios.py
tap_asana/streams/projects.py
tap_asana/streams/sections.py
tap_asana/streams/stories.py
tap_asana/streams/subtasks.py
tap_asana/streams/tags.py
tap_asana/streams/tasks.py
tap_asana/streams/teams.py
tap_asana/streams/users.py
tap_asana/streams/workspaces.py
tests/test_all_fields.py
tests/test_automatic_fields.py
tests/test_bookmarks.py
tests/test_discovery.py
tests/test_interrupted_sync.py
tests/test_start_date.py